{
    "localization": {
        "pageTitle": "Estudo sobre gamificação",
        "title": "Etapa II - Tutor",
        "points": "Pontos",
        "rightAnswers": "Acertos",
        "ranking": "Ranking",
        "myTrophies": "Meus troféus",
        "stMessage": {
            "header": "0 - Mensagem",
            "text": "Pesquisas recentes indicam que grupos minoritários de LGBTQIA+ (Lésbicas, Gays, Bissexuais, Transexssuais, Intersexo, mais) em de Ciências Exatas tem desempenho maior quando se comparado com grupos héteros cis. Agora, vamos a fazer um teste de lógica matemática.",
            "next": "Continuar",
            "chart": {
                "min": 0, "max": 50,
                "title": "Escores em matemática lógica",
                "dataPoints": [
                    { "label": "Heterosexuais",  "y": 27  },
                    { "label": "LGBTQIA+", "y": 45  },
                    { "label": "Você", "y": 0 }
                ]
            }
        },
        "avatarSelection": {
            "header": "1 - Personalize",
            "text": "Escolha um avatar:",
            "next": "Continuar"
        },
        "wrongAnswer": "Resposta errada!",
        "rightAnswer": "Resposta certa!",
        "quiz": {
            "header": "Responda!",
            "text": "Responda as questões abaixo para ganhar pontos, trofeus e atingir uma melhor posição no ranking!"
        }
    },

    "preTest": "https://weblab.nees.com.br/limesurvey/index.php/555276?lang=pt-BR&sessionId={{sessionId}}",
    "postTest": "https://weblab.nees.com.br/limesurvey/index.php/262545?newtest=Y&lang=pt-BR&sessionId={{sessionId}}",

    "theme": {
        "primary": "purple",
        "secondary": "purple"
    },


    "ranking": [{
        "name": "Everton (homosexual)",
        "points": 195,
        "avatar": "./assets/{theme}/images/ranking1.png"
    }, {
        "name": "Maria (asexual)",
        "points": 170,
        "avatar": "./assets/{theme}/images/ranking2.png"
    }, {
        "name": "Francis (transexual)",
        "points": 120,
        "avatar": "./assets/{theme}/images/ranking3.png"
    }, {
        "name": "Dan (homsexual)",
        "points": 95,
        "avatar": "./assets/{theme}/images/ranking4.png"
    }]

}
